[
  {
    "name": "adler32",
    "version": "1.0.3",
    "id": "adler32"
  },
  {
    "name": "aho-corasick",
    "version": "0.7.6",
    "id": "aho_corasick"
  },
  {
    "name": "alga",
    "version": "0.9.1",
    "id": "alga"
  },
  {
    "name": "ansi_term",
    "version": "0.12.0",
    "id": "ansi_term"
  },
  {
    "name": "antidote",
    "version": "1.0.0",
    "id": "antidote"
  },
  {
    "name": "approx",
    "version": "0.3.2",
    "id": "approx"
  },
  {
    "name": "arc-swap",
    "version": "0.3.11",
    "id": "arc_swap"
  },
  {
    "name": "arrayref",
    "version": "0.3.5",
    "id": "arrayref"
  },
  {
    "name": "arrayvec",
    "version": "0.4.11",
    "id": "arrayvec"
  },
  {
    "name": "atty",
    "version": "0.2.13",
    "id": "atty"
  },
  {
    "name": "autocfg",
    "version": "0.1.5",
    "id": "autocfg"
  },
  {
    "name": "backtrace",
    "version": "0.3.34",
    "id": "backtrace"
  },
  {
    "name": "backtrace-sys",
    "version": "0.1.31",
    "id": "backtrace_sys"
  },
  {
    "name": "base64",
    "version": "0.10.1",
    "id": "base64"
  },
  {
    "name": "bit-set",
    "version": "0.5.1",
    "id": "bit_set"
  },
  {
    "name": "bit-vec",
    "version": "0.5.1",
    "id": "bit_vec"
  },
  {
    "name": "bitflags",
    "version": "1.1.0",
    "id": "bitflags"
  },
  {
    "name": "blake2b_simd",
    "version": "0.5.6",
    "id": "blake2b_simd"
  },
  {
    "name": "block-buffer",
    "version": "0.3.3",
    "id": "block_buffer"
  },
  {
    "name": "bstr",
    "version": "0.2.7",
    "id": "bstr"
  },
  {
    "name": "bumpalo",
    "version": "2.5.0",
    "id": "bumpalo"
  },
  {
    "name": "byte-tools",
    "version": "0.2.0",
    "id": "byte_tools"
  },
  {
    "name": "byteorder",
    "version": "1.3.2",
    "id": "byteorder"
  },
  {
    "name": "bytes",
    "version": "0.4.12",
    "id": "bytes"
  },
  {
    "name": "c2-chacha",
    "version": "0.2.2",
    "id": "c2_chacha"
  },
  {
    "name": "cc",
    "version": "1.0.40",
    "id": "cc"
  },
  {
    "name": "cfg-if",
    "version": "0.1.9",
    "id": "cfg_if"
  },
  {
    "name": "chrono",
    "version": "0.4.7",
    "id": "chrono"
  },
  {
    "name": "clap",
    "version": "2.33.0",
    "id": "clap"
  },
  {
    "name": "cloudabi",
    "version": "0.0.3",
    "id": "cloudabi"
  },
  {
    "name": "color_quant",
    "version": "1.0.1",
    "id": "color_quant"
  },
  {
    "name": "constant_time_eq",
    "version": "0.1.3",
    "id": "constant_time_eq"
  },
  {
    "name": "cookie",
    "version": "0.12.0",
    "id": "cookie"
  },
  {
    "name": "cookie_store",
    "version": "0.7.0",
    "id": "cookie_store"
  },
  {
    "name": "crc32fast",
    "version": "1.2.0",
    "id": "crc32fast"
  },
  {
    "name": "crossbeam",
    "version": "0.7.2",
    "id": "crossbeam"
  },
  {
    "name": "crossbeam-channel",
    "version": "0.3.9",
    "id": "crossbeam_channel"
  },
  {
    "name": "crossbeam-deque",
    "version": "0.7.1",
    "id": "crossbeam_deque"
  },
  {
    "name": "crossbeam-epoch",
    "version": "0.7.2",
    "id": "crossbeam_epoch"
  },
  {
    "name": "crossbeam-queue",
    "version": "0.1.2",
    "id": "crossbeam_queue"
  },
  {
    "name": "crossbeam-utils",
    "version": "0.6.6",
    "id": "crossbeam_utils"
  },
  {
    "name": "crypto-mac",
    "version": "0.5.2",
    "id": "crypto_mac"
  },
  {
    "name": "csv",
    "version": "1.1.1",
    "id": "csv"
  },
  {
    "name": "csv-core",
    "version": "0.1.6",
    "id": "csv_core"
  },
  {
    "name": "data-encoding",
    "version": "2.1.2",
    "id": "data_encoding"
  },
  {
    "name": "deflate",
    "version": "0.7.20",
    "id": "deflate"
  },
  {
    "name": "digest",
    "version": "0.7.6",
    "id": "digest"
  },
  {
    "name": "dirs",
    "version": "2.0.2",
    "id": "dirs"
  },
  {
    "name": "dirs-sys",
    "version": "0.3.4",
    "id": "dirs_sys"
  },
  {
    "name": "dtoa",
    "version": "0.4.4",
    "id": "dtoa"
  },
  {
    "name": "either",
    "version": "1.5.2",
    "id": "either"
  },
  {
    "name": "encoding_rs",
    "version": "0.8.17",
    "id": "encoding_rs"
  },
  {
    "name": "env_logger",
    "version": "0.6.2",
    "id": "env_logger"
  },
  {
    "name": "error-chain",
    "version": "0.12.1",
    "id": "error_chain"
  },
  {
    "name": "failure",
    "version": "0.1.5",
    "id": "failure"
  },
  {
    "name": "failure_derive",
    "version": "0.1.5",
    "id": "failure_derive"
  },
  {
    "name": "fake-simd",
    "version": "0.1.2",
    "id": "fake_simd"
  },
  {
    "name": "fallible-iterator",
    "version": "0.2.0",
    "id": "fallible_iterator"
  },
  {
    "name": "fallible-streaming-iterator",
    "version": "0.1.9",
    "id": "fallible_streaming_iterator"
  },
  {
    "name": "filetime",
    "version": "0.2.7",
    "id": "filetime"
  },
  {
    "name": "flate2",
    "version": "1.0.11",
    "id": "flate2"
  },
  {
    "name": "fnv",
    "version": "1.0.6",
    "id": "fnv"
  },
  {
    "name": "foreign-types",
    "version": "0.3.2",
    "id": "foreign_types"
  },
  {
    "name": "foreign-types-shared",
    "version": "0.1.1",
    "id": "foreign_types_shared"
  },
  {
    "name": "fuchsia-cprng",
    "version": "0.1.1",
    "id": "fuchsia_cprng"
  },
  {
    "name": "fuchsia-zircon",
    "version": "0.3.3",
    "id": "fuchsia_zircon"
  },
  {
    "name": "fuchsia-zircon-sys",
    "version": "0.3.3",
    "id": "fuchsia_zircon_sys"
  },
  {
    "name": "futf",
    "version": "0.1.4",
    "id": "futf"
  },
  {
    "name": "futures",
    "version": "0.1.28",
    "id": "futures"
  },
  {
    "name": "futures-cpupool",
    "version": "0.1.8",
    "id": "futures_cpupool"
  },
  {
    "name": "gcc",
    "version": "0.3.55",
    "id": "gcc"
  },
  {
    "name": "generic-array",
    "version": "0.12.3",
    "id": "generic_array"
  },
  {
    "name": "getrandom",
    "version": "0.1.10",
    "id": "getrandom"
  },
  {
    "name": "gif",
    "version": "0.10.2",
    "id": "gif"
  },
  {
    "name": "glob",
    "version": "0.3.0",
    "id": "glob"
  },
  {
    "name": "h2",
    "version": "0.1.26",
    "id": "h2"
  },
  {
    "name": "heck",
    "version": "0.3.1",
    "id": "heck"
  },
  {
    "name": "hex",
    "version": "0.2.0",
    "id": "hex"
  },
  {
    "name": "hmac",
    "version": "0.5.0",
    "id": "hmac"
  },
  {
    "name": "html5ever",
    "version": "0.23.0",
    "id": "html5ever"
  },
  {
    "name": "http",
    "version": "0.1.18",
    "id": "http"
  },
  {
    "name": "http-body",
    "version": "0.1.0",
    "id": "http_body"
  },
  {
    "name": "httparse",
    "version": "1.3.4",
    "id": "httparse"
  },
  {
    "name": "humantime",
    "version": "1.2.0",
    "id": "humantime"
  },
  {
    "name": "hyper",
    "version": "0.12.33",
    "id": "hyper"
  },
  {
    "name": "hyper-tls",
    "version": "0.3.2",
    "id": "hyper_tls"
  },
  {
    "name": "idna",
    "version": "0.2.0",
    "id": "idna"
  },
  {
    "name": "image",
    "version": "0.22.1",
    "id": "image"
  },
  {
    "name": "indexmap",
    "version": "1.0.2",
    "id": "indexmap"
  },
  {
    "name": "inflate",
    "version": "0.4.5",
    "id": "inflate"
  },
  {
    "name": "iovec",
    "version": "0.1.2",
    "id": "iovec"
  },
  {
    "name": "itertools",
    "version": "0.8.0",
    "id": "itertools"
  },
  {
    "name": "itoa",
    "version": "0.4.4",
    "id": "itoa"
  },
  {
    "name": "jpeg-decoder",
    "version": "0.1.15",
    "id": "jpeg_decoder"
  },
  {
    "name": "js-sys",
    "version": "0.3.26",
    "id": "js_sys"
  },
  {
    "name": "kernel32-sys",
    "version": "0.2.2",
    "id": "kernel32"
  },
  {
    "name": "lazy_static",
    "version": "1.3.0",
    "id": "lazy_static"
  },
  {
    "name": "lazycell",
    "version": "1.2.1",
    "id": "lazycell"
  },
  {
    "name": "libc",
    "version": "0.2.62",
    "id": "libc"
  },
  {
    "name": "libm",
    "version": "0.1.4",
    "id": "libm"
  },
  {
    "name": "libsqlite3-sys",
    "version": "0.16.0",
    "id": "libsqlite3_sys"
  },
  {
    "name": "linked-hash-map",
    "version": "0.5.2",
    "id": "linked_hash_map"
  },
  {
    "name": "lock_api",
    "version": "0.3.1",
    "id": "lock_api"
  },
  {
    "name": "log",
    "version": "0.4.8",
    "id": "log"
  },
  {
    "name": "log-mdc",
    "version": "0.1.0",
    "id": "log_mdc"
  },
  {
    "name": "log4rs",
    "version": "0.8.3",
    "id": "log4rs"
  },
  {
    "name": "lru-cache",
    "version": "0.1.2",
    "id": "lru_cache"
  },
  {
    "name": "lzw",
    "version": "0.10.0",
    "id": "lzw"
  },
  {
    "name": "mac",
    "version": "0.1.1",
    "id": "mac"
  },
  {
    "name": "markup5ever",
    "version": "0.8.1",
    "id": "markup5ever"
  },
  {
    "name": "matches",
    "version": "0.1.8",
    "id": "matches"
  },
  {
    "name": "matrixmultiply",
    "version": "0.2.2",
    "id": "matrixmultiply"
  },
  {
    "name": "md5",
    "version": "0.3.8",
    "id": "md5"
  },
  {
    "name": "memchr",
    "version": "2.2.1",
    "id": "memchr"
  },
  {
    "name": "memmap",
    "version": "0.7.0",
    "id": "memmap"
  },
  {
    "name": "memoffset",
    "version": "0.5.1",
    "id": "memoffset"
  },
  {
    "name": "mime",
    "version": "0.3.13",
    "id": "mime"
  },
  {
    "name": "mime_guess",
    "version": "2.0.1",
    "id": "mime_guess"
  },
  {
    "name": "miniz-sys",
    "version": "0.1.12",
    "id": "miniz_sys"
  },
  {
    "name": "miniz_oxide",
    "version": "0.3.2",
    "id": "miniz_oxide"
  },
  {
    "name": "mio",
    "version": "0.6.19",
    "id": "mio"
  },
  {
    "name": "miow",
    "version": "0.2.1",
    "id": "miow"
  },
  {
    "name": "nalgebra",
    "version": "0.18.0",
    "id": "nalgebra"
  },
  {
    "name": "native-tls",
    "version": "0.2.3",
    "id": "native_tls"
  },
  {
    "name": "ndarray",
    "version": "0.12.1",
    "id": "ndarray"
  },
  {
    "name": "net2",
    "version": "0.2.33",
    "id": "net2"
  },
  {
    "name": "new_debug_unreachable",
    "version": "1.0.3",
    "id": "debug_unreachable"
  },
  {
    "name": "nodrop",
    "version": "0.1.13",
    "id": "nodrop"
  },
  {
    "name": "nom",
    "version": "4.2.3",
    "id": "nom"
  },
  {
    "name": "num",
    "version": "0.2.0",
    "id": "num"
  },
  {
    "name": "num-bigint",
    "version": "0.2.2",
    "id": "num_bigint"
  },
  {
    "name": "num-complex",
    "version": "0.2.3",
    "id": "num_complex"
  },
  {
    "name": "num-derive",
    "version": "0.2.5",
    "id": "num_derive"
  },
  {
    "name": "num-integer",
    "version": "0.1.41",
    "id": "num_integer"
  },
  {
    "name": "num-iter",
    "version": "0.1.39",
    "id": "num_iter"
  },
  {
    "name": "num-rational",
    "version": "0.2.2",
    "id": "num_rational"
  },
  {
    "name": "num-traits",
    "version": "0.2.8",
    "id": "num_traits"
  },
  {
    "name": "num_cpus",
    "version": "1.10.1",
    "id": "num_cpus"
  },
  {
    "name": "openssl",
    "version": "0.10.24",
    "id": "openssl"
  },
  {
    "name": "openssl-probe",
    "version": "0.1.2",
    "id": "openssl_probe"
  },
  {
    "name": "openssl-sys",
    "version": "0.9.49",
    "id": "openssl_sys"
  },
  {
    "name": "ordered-float",
    "version": "1.0.2",
    "id": "ordered_float"
  },
  {
    "name": "owning_ref",
    "version": "0.4.0",
    "id": "owning_ref"
  },
  {
    "name": "parking_lot",
    "version": "0.9.0",
    "id": "parking_lot"
  },
  {
    "name": "parking_lot_core",
    "version": "0.6.2",
    "id": "parking_lot_core"
  },
  {
    "name": "percent-encoding",
    "version": "2.1.0",
    "id": "percent_encoding"
  },
  {
    "name": "phf",
    "version": "0.7.24",
    "id": "phf"
  },
  {
    "name": "phf_codegen",
    "version": "0.7.24",
    "id": "phf_codegen"
  },
  {
    "name": "phf_generator",
    "version": "0.7.24",
    "id": "phf_generator"
  },
  {
    "name": "phf_shared",
    "version": "0.7.24",
    "id": "phf_shared"
  },
  {
    "name": "pkg-config",
    "version": "0.3.15",
    "id": "pkg_config"
  },
  {
    "name": "png",
    "version": "0.15.0",
    "id": "png"
  },
  {
    "name": "postgres",
    "version": "0.15.2",
    "id": "postgres"
  },
  {
    "name": "postgres-protocol",
    "version": "0.3.2",
    "id": "postgres_protocol"
  },
  {
    "name": "postgres-shared",
    "version": "0.4.2",
    "id": "postgres_shared"
  },
  {
    "name": "ppv-lite86",
    "version": "0.2.5",
    "id": "ppv_lite86"
  },
  {
    "name": "precomputed-hash",
    "version": "0.1.1",
    "id": "precomputed_hash"
  },
  {
    "name": "proc-macro2",
    "version": "1.0.1",
    "id": "proc_macro2"
  },
  {
    "name": "publicsuffix",
    "version": "1.5.2",
    "id": "publicsuffix"
  },
  {
    "name": "quick-error",
    "version": "1.2.2",
    "id": "quick_error"
  },
  {
    "name": "quote",
    "version": "1.0.2",
    "id": "quote"
  },
  {
    "name": "rand",
    "version": "0.7.0",
    "id": "rand"
  },
  {
    "name": "rand_chacha",
    "version": "0.2.1",
    "id": "rand_chacha"
  },
  {
    "name": "rand_core",
    "version": "0.5.0",
    "id": "rand_core"
  },
  {
    "name": "rand_hc",
    "version": "0.2.0",
    "id": "rand_hc"
  },
  {
    "name": "rand_isaac",
    "version": "0.1.1",
    "id": "rand_isaac"
  },
  {
    "name": "rand_jitter",
    "version": "0.1.4",
    "id": "rand_jitter"
  },
  {
    "name": "rand_os",
    "version": "0.1.3",
    "id": "rand_os"
  },
  {
    "name": "rand_pcg",
    "version": "0.1.2",
    "id": "rand_pcg"
  },
  {
    "name": "rand_xorshift",
    "version": "0.1.1",
    "id": "rand_xorshift"
  },
  {
    "name": "rawpointer",
    "version": "0.1.0",
    "id": "rawpointer"
  },
  {
    "name": "rayon",
    "version": "1.1.0",
    "id": "rayon"
  },
  {
    "name": "rayon-core",
    "version": "1.5.0",
    "id": "rayon_core"
  },
  {
    "name": "rdrand",
    "version": "0.4.0",
    "id": "rdrand"
  },
  {
    "name": "regex",
    "version": "1.2.1",
    "id": "regex"
  },
  {
    "name": "regex-automata",
    "version": "0.1.8",
    "id": "regex_automata"
  },
  {
    "name": "regex-syntax",
    "version": "0.6.11",
    "id": "regex_syntax"
  },
  {
    "name": "remove_dir_all",
    "version": "0.5.2",
    "id": "remove_dir_all"
  },
  {
    "name": "reqwest",
    "version": "0.9.19",
    "id": "reqwest"
  },
  {
    "name": "ring",
    "version": "0.16.7",
    "id": "ring"
  },
  {
    "name": "rusqlite",
    "version": "0.20.0",
    "id": "rusqlite"
  },
  {
    "name": "rust-argon2",
    "version": "0.5.1",
    "id": "argon2"
  },
  {
    "name": "rustc-demangle",
    "version": "0.1.16",
    "id": "rustc_demangle"
  },
  {
    "name": "rustc-serialize",
    "version": "0.3.24",
    "id": "rustc_serialize"
  },
  {
    "name": "rustc_version",
    "version": "0.2.3",
    "id": "rustc_version"
  },
  {
    "name": "ryu",
    "version": "1.0.0",
    "id": "ryu"
  },
  {
    "name": "safemem",
    "version": "0.2.0",
    "id": "safemem"
  },
  {
    "name": "same-file",
    "version": "1.0.5",
    "id": "same_file"
  },
  {
    "name": "schannel",
    "version": "0.1.15",
    "id": "schannel"
  },
  {
    "name": "scoped_threadpool",
    "version": "0.1.9",
    "id": "scoped_threadpool"
  },
  {
    "name": "scopeguard",
    "version": "1.0.0",
    "id": "scopeguard"
  },
  {
    "name": "select",
    "version": "0.4.3",
    "id": "select"
  },
  {
    "name": "semver",
    "version": "0.9.0",
    "id": "semver"
  },
  {
    "name": "semver-parser",
    "version": "0.9.0",
    "id": "semver_parser"
  },
  {
    "name": "serde",
    "version": "1.0.99",
    "id": "serde"
  },
  {
    "name": "serde-value",
    "version": "0.5.3",
    "id": "serde_value"
  },
  {
    "name": "serde_derive",
    "version": "1.0.99",
    "id": "serde_derive"
  },
  {
    "name": "serde_json",
    "version": "1.0.40",
    "id": "serde_json"
  },
  {
    "name": "serde_urlencoded",
    "version": "0.5.5",
    "id": "serde_urlencoded"
  },
  {
    "name": "serde_yaml",
    "version": "0.8.9",
    "id": "serde_yaml"
  },
  {
    "name": "sha2",
    "version": "0.7.1",
    "id": "sha2"
  },
  {
    "name": "siphasher",
    "version": "0.2.3",
    "id": "siphasher"
  },
  {
    "name": "slab",
    "version": "0.4.2",
    "id": "slab"
  },
  {
    "name": "smallvec",
    "version": "0.6.10",
    "id": "smallvec"
  },
  {
    "name": "socket2",
    "version": "0.3.11",
    "id": "socket2"
  },
  {
    "name": "sourcefile",
    "version": "0.1.4",
    "id": "sourcefile"
  },
  {
    "name": "spin",
    "version": "0.5.1",
    "id": "spin"
  },
  {
    "name": "stable_deref_trait",
    "version": "1.1.1",
    "id": "stable_deref_trait"
  },
  {
    "name": "string",
    "version": "0.2.1",
    "id": "string"
  },
  {
    "name": "string_cache",
    "version": "0.7.3",
    "id": "string_cache"
  },
  {
    "name": "string_cache_codegen",
    "version": "0.4.2",
    "id": "string_cache_codegen"
  },
  {
    "name": "string_cache_shared",
    "version": "0.3.0",
    "id": "string_cache_shared"
  },
  {
    "name": "stringprep",
    "version": "0.1.2",
    "id": "stringprep"
  },
  {
    "name": "strsim",
    "version": "0.9.2",
    "id": "strsim"
  },
  {
    "name": "syn",
    "version": "1.0.3",
    "id": "syn"
  },
  {
    "name": "synstructure",
    "version": "0.12.0",
    "id": "synstructure"
  },
  {
    "name": "syslog",
    "version": "4.0.1",
    "id": "syslog"
  },
  {
    "name": "tar",
    "version": "0.4.26",
    "id": "tar"
  },
  {
    "name": "tempdir",
    "version": "0.3.7",
    "id": "tempdir"
  },
  {
    "name": "tempfile",
    "version": "3.1.0",
    "id": "tempfile"
  },
  {
    "name": "tendril",
    "version": "0.4.1",
    "id": "tendril"
  },
  {
    "name": "term",
    "version": "0.6.1",
    "id": "term"
  },
  {
    "name": "termcolor",
    "version": "1.0.5",
    "id": "termcolor"
  },
  {
    "name": "textwrap",
    "version": "0.11.0",
    "id": "textwrap"
  },
  {
    "name": "thread-id",
    "version": "3.3.0",
    "id": "thread_id"
  },
  {
    "name": "thread_local",
    "version": "0.3.6",
    "id": "thread_local"
  },
  {
    "name": "threadpool",
    "version": "1.7.1",
    "id": "threadpool"
  },
  {
    "name": "tiff",
    "version": "0.3.1",
    "id": "tiff"
  },
  {
    "name": "time",
    "version": "0.1.42",
    "id": "time"
  },
  {
    "name": "tokio",
    "version": "0.1.22",
    "id": "tokio"
  },
  {
    "name": "tokio-buf",
    "version": "0.1.1",
    "id": "tokio_buf"
  },
  {
    "name": "tokio-current-thread",
    "version": "0.1.6",
    "id": "tokio_current_thread"
  },
  {
    "name": "tokio-executor",
    "version": "0.1.8",
    "id": "tokio_executor"
  },
  {
    "name": "tokio-io",
    "version": "0.1.12",
    "id": "tokio_io"
  },
  {
    "name": "tokio-reactor",
    "version": "0.1.9",
    "id": "tokio_reactor"
  },
  {
    "name": "tokio-sync",
    "version": "0.1.6",
    "id": "tokio_sync"
  },
  {
    "name": "tokio-tcp",
    "version": "0.1.3",
    "id": "tokio_tcp"
  },
  {
    "name": "tokio-threadpool",
    "version": "0.1.15",
    "id": "tokio_threadpool"
  },
  {
    "name": "tokio-timer",
    "version": "0.2.11",
    "id": "tokio_timer"
  },
  {
    "name": "toml",
    "version": "0.5.3",
    "id": "toml"
  },
  {
    "name": "traitobject",
    "version": "0.1.0",
    "id": "traitobject"
  },
  {
    "name": "try-lock",
    "version": "0.2.2",
    "id": "try_lock"
  },
  {
    "name": "try_from",
    "version": "0.3.2",
    "id": "try_from"
  },
  {
    "name": "typemap",
    "version": "0.3.3",
    "id": "typemap"
  },
  {
    "name": "typenum",
    "version": "1.10.0",
    "id": "typenum"
  },
  {
    "name": "ucd-util",
    "version": "0.1.5",
    "id": "ucd_util"
  },
  {
    "name": "unicase",
    "version": "2.4.0",
    "id": "unicase"
  },
  {
    "name": "unicode-bidi",
    "version": "0.3.4",
    "id": "unicode_bidi"
  },
  {
    "name": "unicode-normalization",
    "version": "0.1.8",
    "id": "unicode_normalization"
  },
  {
    "name": "unicode-segmentation",
    "version": "1.3.0",
    "id": "unicode_segmentation"
  },
  {
    "name": "unicode-width",
    "version": "0.1.5",
    "id": "unicode_width"
  },
  {
    "name": "unicode-xid",
    "version": "0.2.0",
    "id": "unicode_xid"
  },
  {
    "name": "unreachable",
    "version": "1.0.0",
    "id": "unreachable"
  },
  {
    "name": "unsafe-any",
    "version": "0.4.2",
    "id": "unsafe_any"
  },
  {
    "name": "untrusted",
    "version": "0.7.0",
    "id": "untrusted"
  },
  {
    "name": "url",
    "version": "2.1.0",
    "id": "url"
  },
  {
    "name": "utf-8",
    "version": "0.7.5",
    "id": "utf8"
  },
  {
    "name": "utf8-ranges",
    "version": "1.0.4",
    "id": "utf8_ranges"
  },
  {
    "name": "uuid",
    "version": "0.7.4",
    "id": "uuid"
  },
  {
    "name": "vcpkg",
    "version": "0.2.7",
    "id": "vcpkg"
  },
  {
    "name": "vec_map",
    "version": "0.8.1",
    "id": "vec_map"
  },
  {
    "name": "version_check",
    "version": "0.9.1",
    "id": "version_check"
  },
  {
    "name": "void",
    "version": "1.0.2",
    "id": "void"
  },
  {
    "name": "walkdir",
    "version": "2.2.9",
    "id": "walkdir"
  },
  {
    "name": "want",
    "version": "0.2.0",
    "id": "want"
  },
  {
    "name": "wasi",
    "version": "0.5.0",
    "id": "wasi"
  },
  {
    "name": "wasm-bindgen",
    "version": "0.2.49",
    "id": "wasm_bindgen"
  },
  {
    "name": "wasm-bindgen-backend",
    "version": "0.2.49",
    "id": "wasm_bindgen_backend"
  },
  {
    "name": "wasm-bindgen-macro",
    "version": "0.2.49",
    "id": "wasm_bindgen_macro"
  },
  {
    "name": "wasm-bindgen-macro-support",
    "version": "0.2.49",
    "id": "wasm_bindgen_macro_support"
  },
  {
    "name": "wasm-bindgen-shared",
    "version": "0.2.49",
    "id": "wasm_bindgen_shared"
  },
  {
    "name": "wasm-bindgen-webidl",
    "version": "0.2.49",
    "id": "wasm_bindgen_webidl"
  },
  {
    "name": "web-sys",
    "version": "0.3.26",
    "id": "web_sys"
  },
  {
    "name": "weedle",
    "version": "0.10.0",
    "id": "weedle"
  },
  {
    "name": "winapi",
    "version": "0.3.7",
    "id": "winapi"
  },
  {
    "name": "winapi-build",
    "version": "0.1.1",
    "id": "build"
  },
  {
    "name": "winapi-i686-pc-windows-gnu",
    "version": "0.4.0",
    "id": "winapi_i686_pc_windows_gnu"
  },
  {
    "name": "winapi-util",
    "version": "0.1.2",
    "id": "winapi_util"
  },
  {
    "name": "winapi-x86_64-pc-windows-gnu",
    "version": "0.4.0",
    "id": "winapi_x86_64_pc_windows_gnu"
  },
  {
    "name": "wincolor",
    "version": "1.0.2",
    "id": "wincolor"
  },
  {
    "name": "ws2_32-sys",
    "version": "0.2.1",
    "id": "ws2_32"
  },
  {
    "name": "xattr",
    "version": "0.2.2",
    "id": "xattr"
  },
  {
    "name": "yaml-rust",
    "version": "0.4.3",
    "id": "yaml_rust"
  }
]